pytest_loop/__init__.py
pytest_loop/py.typed
pytest_loop-1.0.13.dist-info/METADATA
pytest_loop-1.0.13.dist-info/WHEEL
pytest_loop-1.0.13.dist-info/entry_points.txt
pytest_loop-1.0.13.dist-info/licenses/LICENSE
pytest_loop-1.0.13.dist-info/RECORD
