Metadata-Version: 2.3
Name: pytest-loop
Version: 1.0.13
Summary: pytest plugin for looping tests
Project-URL: Homepage, https://github.com/anogowski/pytest-loop
Project-URL: Repository, https://github.com/anogowski/pytest-loop.git
Project-URL: Issues, https://github.com/anogowski/pytest-loop/issues
Project-URL: Changelog, https://github.com/anogowski/pytest-loop/blob/master/CHANGELOG.rst
Author: Adam Nogowski
License: This Source Code Form is subject to the terms of the Mozilla Public
License-File: LICENSE
Keywords: duration,loop,pytest,pytest-loop,pytest-repeat,pytest-rerun,pytest-stress,repeat,rerun,stress,test,time
Classifier: Development Status :: 5 - Production/Stable
Classifier: Framework :: Pytest
Classifier: Intended Audience :: Developers
Classifier: License :: OSI Approved :: Mozilla Public License 2.0 (MPL 2.0)
Classifier: Operating System :: MacOS :: MacOS X
Classifier: Operating System :: Microsoft :: Windows
Classifier: Operating System :: POSIX
Classifier: Programming Language :: Python
Classifier: Programming Language :: Python :: 3 :: Only
Classifier: Programming Language :: Python :: 3.7
Classifier: Programming Language :: Python :: 3.8
Classifier: Programming Language :: Python :: 3.9
Classifier: Programming Language :: Python :: 3.10
Classifier: Programming Language :: Python :: 3.11
Classifier: Programming Language :: Python :: 3.12
Classifier: Programming Language :: Python :: 3.13
Classifier: Topic :: Software Development :: Quality Assurance
Classifier: Topic :: Software Development :: Testing
Classifier: Topic :: Utilities
Requires-Python: >=3.7
Requires-Dist: pytest
